LICENSE
README.md
main.py
setup.cfg
setup.py
clot_terminal.egg-info/PKG-INFO
clot_terminal.egg-info/SOURCES.txt
clot_terminal.egg-info/dependency_links.txt
clot_terminal.egg-info/entry_points.txt
clot_terminal.egg-info/requires.txt
clot_terminal.egg-info/top_level.txt