Metadata-Version: 2.1
Name: clot-terminal
Version: 0.0.2
Summary: A Colorfull Terminal ~ on the rise...
Home-page: https://github.com/merwin-asm/Clot
Author: Cactochan
License: UNKNOWN
Keywords: terminal,clot,colorfull,color,cool,commands,commandline
Platform: any
Classifier: Programming Language :: Python :: 3
Requires-Python: >=3.8
License-File: LICENSE
